dajapy/__init__.py
dajapy/shareka.py
dajapy-0.1.1.dist-info/WHEEL
dajapy-0.1.1.dist-info/METADATA
dajapy-0.1.1.dist-info/RECORD
